sensitivity_calculator/__init__.py
sensitivity_calculator/ad_fns.py
sensitivity_calculator/noise.py
sensitivity_calculator/pwvCalculator.py
sensitivity_calculator/sensitivity.py
sensitivity_calculator-0.0.2.dist-info/LICENSE
sensitivity_calculator-0.0.2.dist-info/METADATA
sensitivity_calculator-0.0.2.dist-info/WHEEL
sensitivity_calculator-0.0.2.dist-info/top_level.txt
sensitivity_calculator-0.0.2.dist-info/RECORD
